LICENSE
MANIFEST.in
README.rst
setup.py
RNAscrutiny/__init__.py
RNAscrutiny/grn.py
RNAscrutiny/infer.py
RNAscrutiny/plotting.py
RNAscrutiny/pseudotime.py
RNAscrutiny/simulate.py
RNAscrutiny/tree.py
RNAscrutiny.egg-info/PKG-INFO
RNAscrutiny.egg-info/SOURCES.txt
RNAscrutiny.egg-info/dependency_links.txt
RNAscrutiny.egg-info/not-zip-safe
RNAscrutiny.egg-info/requires.txt
RNAscrutiny.egg-info/top_level.txt
doc/conf.py
doc/examples.rst
doc/index.rst
doc/tutorial.rst