Metadata-Version: 1.0
Name: RNAscrutiny
Version: 1.3
Summary: Tool for simulating and analyzing single-cell RNA-sequencing data.
Home-page: http://lbm.niddk.nih.gov/mckennajp/scRutiNy
Author: Joseph P McKena
Author-email: joseph.mckenna@nih.gov
License: MIT
Keywords: RNA single cell simulation inference generative genomics transcriptomics
Platform: UNKNOWN
